.gitignore
MANIFEST.in
setup.py
ebs/__init__.py
ebs/linuxnode/__init__.py
ebs/linuxnode/gui/__init__.py
ebs/linuxnode/gui/kivy/__init__.py
ebs/linuxnode/gui/kivy/netconfig/__init__.py
ebs/linuxnode/gui/kivy/netconfig/mixin.py
ebs/linuxnode/gui/kivy/netconfig/images/close.png
ebs/linuxnode/gui/kivy/netconfig/images/settings.png
ebs_linuxnode_gui_kivy_netconfig.egg-info/PKG-INFO
ebs_linuxnode_gui_kivy_netconfig.egg-info/SOURCES.txt
ebs_linuxnode_gui_kivy_netconfig.egg-info/dependency_links.txt
ebs_linuxnode_gui_kivy_netconfig.egg-info/requires.txt
ebs_linuxnode_gui_kivy_netconfig.egg-info/top_level.txt
example/app.py
example/node.py
example/run.py