Metadata-Version: 1.1
Name: ebs-linuxnode-gui-kivy-netconfig
Version: 1.2.0
Summary: NetConfig integration for interactive EBS Linuxnode Kivy Applications
Home-page: https://github.com/ebs-universe/ebs-linuxnode-kivy-netconfig
Author: Chintalagiri Shashank
Author-email: shashank.chintalagiri@gmail.com
License: UNKNOWN
Platform: UNKNOWN
Classifier: Development Status :: 5 - Production/Stable
Classifier: Intended Audience :: Developers
Classifier: License :: OSI Approved :: GNU General Public License v3 or later (GPLv3+)
Classifier: Programming Language :: Python
Classifier: Programming Language :: Python :: 3
Classifier: Programming Language :: Python :: 3.6
Classifier: Operating System :: POSIX :: Linux
